pnu_true-1.1.0.data/data/man/man1/false.1.gz
pnu_true-1.1.0.data/data/man/man1/true.1.gz
true/__init__.py
true/main.py
pnu_true-1.1.0.dist-info/License
pnu_true-1.1.0.dist-info/METADATA
pnu_true-1.1.0.dist-info/WHEEL
pnu_true-1.1.0.dist-info/entry_points.txt
pnu_true-1.1.0.dist-info/top_level.txt
pnu_true-1.1.0.dist-info/RECORD
